btx_lib_list/__init__.py
btx_lib_list/__init__conf__.py
btx_lib_list/__main__.py
btx_lib_list/behaviors.py
btx_lib_list/cli.py
btx_lib_list/lib_list.py
btx_lib_list/py.typed
btx_lib_list-1.0.1.dist-info/METADATA
btx_lib_list-1.0.1.dist-info/WHEEL
btx_lib_list-1.0.1.dist-info/entry_points.txt
btx_lib_list-1.0.1.dist-info/licenses/LICENSE
btx_lib_list-1.0.1.dist-info/RECORD
