Metadata-Version: 2.4
Name: btx_lib_list
Version: 1.0.1
Summary: Small helpers for list managment
Project-URL: Homepage, https://github.com/bitranox/btx_lib_list
Project-URL: Repository, https://github.com/bitranox/btx_lib_list.git
Project-URL: Issues, https://github.com/bitranox/btx_lib_list/issues
Author-email: bitranox <bitranox@gmail.com>
License: MIT
License-File: LICENSE
Keywords: ansi,cli,logging,rich,terminal
Classifier: Environment :: Console
Classifier: License :: OSI Approved :: MIT License
Classifier: Operating System :: OS Independent
Classifier: Programming Language :: Python :: 3
Classifier: Programming Language :: Python :: 3 :: Only
Classifier: Typing :: Typed
Requires-Python: >=3.13
Requires-Dist: lib-cli-exit-tools>=2.1.0
Requires-Dist: rich-click>=1.9.3
Provides-Extra: dev
Requires-Dist: bandit>=1.8.6; extra == 'dev'
Requires-Dist: build>=1.3.0; extra == 'dev'
Requires-Dist: codecov-cli>=11.2.3; extra == 'dev'
Requires-Dist: import-linter>=2.5.2; extra == 'dev'
Requires-Dist: pip-audit>=2.9.0; extra == 'dev'
Requires-Dist: pyright>=1.1.406; extra == 'dev'
Requires-Dist: pytest-cov>=7.0.0; extra == 'dev'
Requires-Dist: pytest>=8.4.2; extra == 'dev'
Requires-Dist: ruff>=0.14.0; extra == 'dev'
Requires-Dist: textual>=6.3.0; extra == 'dev'
Requires-Dist: twine>=6.2.0; extra == 'dev'
